README.md
setup.py
pyoperator/__init__.py
pyoperator/mylogger.py
pyoperator/myoperator.py
pyoperator.egg-info/PKG-INFO
pyoperator.egg-info/SOURCES.txt
pyoperator.egg-info/dependency_links.txt
pyoperator.egg-info/not-zip-safe
pyoperator.egg-info/requires.txt
pyoperator.egg-info/top_level.txt