Metadata-Version: 1.0
Name: pyoperator
Version: 0.1
Summary: Python wrapper for MyOperator
Home-page: https://bitbucket.org/vtadeshpandey/pyoperator
Author: Adesh Pandey
Author-email: adesh.pandey@myoperator.co
License: PROPRIETARY
Platform: UNKNOWN
